moosir_feature/__init__.py
moosir_feature/model_validations/__init__.py
moosir_feature/model_validations/basic_parameter_searcher.py
moosir_feature/model_validations/benchmarking.py
moosir_feature/model_validations/metrics.py
moosir_feature/model_validations/model_cv_runner.py
moosir_feature/model_validations/model_validator.py
moosir_feature/news_feature/__init__.py
moosir_feature/news_feature/app_settings.py
moosir_feature/news_feature/data_access.py
moosir_feature/news_feature/feature_extractor_news.py
moosir_feature/news_feature/news_manager.py
moosir_feature/trades/__init__.py
moosir_feature/trades/alpha_manager.py
moosir_feature/transformers/__init__.py
moosir_feature/transformers/basic_features/feature_calculator.py
moosir_feature/transformers/feature_cleaning/data_cleaner.py
moosir_feature/transformers/feature_cleaning/feature_cleaner.py
moosir_feature/transformers/feature_selections/feature_selector.py
moosir_feature/transformers/features_common/calculator.py
moosir_feature/transformers/features_cv/feature_cv_manager.py
moosir_feature/transformers/indicators/__main__.py
moosir_feature/transformers/indicators/constants.py
moosir_feature/transformers/indicators/contexts.py
moosir_feature/transformers/indicators/feature_calculator.py
moosir_feature/transformers/indicators/feature_manager.py
moosir_feature/transformers/indicators/tech_indicators.py
moosir_feature/transformers/managers/feature_cv_manager.py
moosir_feature/transformers/managers/feature_manager.py
moosir_feature/transformers/managers/settings.py
moosir_feature/transformers/signal_features/__init__.py
moosir_feature/transformers/signal_features/core.py
moosir_feature/transformers/signal_features/feature_calculator.py
moosir_feature/transformers/signal_features/feature_manager.py
moosir_feature/transformers/tsfresh_features/__init__.py
moosir_feature/transformers/tsfresh_features/feature_calculator.py
moosir_feature/transformers/tsfresh_features/feature_manager.py
moosir_feature-1.4.35.dist-info/LICENSE.txt
moosir_feature-1.4.35.dist-info/METADATA
moosir_feature-1.4.35.dist-info/WHEEL
moosir_feature-1.4.35.dist-info/top_level.txt
moosir_feature-1.4.35.dist-info/RECORD
