Metadata-Version: 2.1
Name: moosir-feature
Version: 1.4.35
Summary: Add a short description here!
Home-page: https://github.com/pyscaffold/pyscaffold/
Author: aliabdoli
Author-email: ali.abdoli.aust@gmail.com
License: MIT
Project-URL: Documentation, https://pyscaffold.org/
Platform: any
Classifier: Development Status :: 4 - Beta
Classifier: Programming Language :: Python
License-File: LICENSE.txt
Requires-Dist: importlib-metadata
Requires-Dist: python-version (<3.8)
Requires-Dist: pandas
Requires-Dist: numpy
Requires-Dist: tsfresh
Requires-Dist: statsmodels
Requires-Dist: filterpy
Requires-Dist: scikit-learn
Requires-Dist: streamlit
Requires-Dist: investpy
Provides-Extra: testing
Requires-Dist: setuptools ; extra == 'testing'
Requires-Dist: pytest ; extra == 'testing'
Requires-Dist: pytest-cov ; extra == 'testing'
Requires-Dist: pandas ; extra == 'testing'
Requires-Dist: numpy ; extra == 'testing'
Requires-Dist: tsfresh ; extra == 'testing'
Requires-Dist: statsmodels ; extra == 'testing'
Requires-Dist: filterpy ; extra == 'testing'
Requires-Dist: scikit-learn ; extra == 'testing'
Requires-Dist: streamlit ; extra == 'testing'
Requires-Dist: investpy ; extra == 'testing'
